{
  "unit": "Kilometres",
  "scale": " ",
  "data": {
    "1984": " ",
    "1985": " ",
    "1986": " ",
    "1987": " ",
    "1988": " ",
    "1989": " ",
    "1990": " ",
    "1991": " ",
    "1992": " ",
    "1993": " ",
    "1994": " ",
    "1995": " ",
    "1996": " ",
    "1997": " ",
    "1998": " ",
    "1999": " ",
    "2000": " ",
    "2001": " ",
    "2002": "3,206",
    "2003": "3,206",
    "2004": "3,215",
    "2005": "3,547",
    "2006": "3,119",
    "2007": "3,150",
    "2008": "3,137",
    "2009": "3,164",
    "2010": "3,194",
    "2011": "3,236",
    "2012": "3,183",
    "2013": "3,169",
    "2014": "3,204",
    "2015": "3,204",
    "2016": "3,204",
    "2017": "3,204",
    "2018": "3,204.00",
    "2019": "3,255",
    "2020": "3,309.00",
    "2021": "3,300",
    "2022": " ",
    "2023": " ",
    "2024": " "
  }
}