{
  "unit": "Rs.",
  "scale": "Million",
  "data": {
    "1990": " ",
    "1991": " ",
    "1992": " ",
    "1993": " ",
    "1994": " ",
    "1995": " ",
    "1996": " ",
    "1997": " ",
    "1998": " ",
    "1999": " ",
    "2000": " ",
    "2001": " ",
    "2002": "162,153.00",
    "2003": "193,025.60",
    "2004": "220,159.40",
    "2005": "256,050.60",
    "2006": "309,427.90",
    "2007": "366,144.58",
    "2008": "457,318.70",
    "2009": "526,546.30",
    "2010": "597,573.18",
    "2011": "702,045.73",
    "2012": "806,592.10",
    "2013": "925,272.91",
    "2014": "1,038,185.80",
    "2015": "1,134,523",
    "2016": " ",
    "2017": " ",
    "2018": " ",
    "2019": " ",
    "2020": " ",
    "2021": " ",
    "2022": " ",
    "2023": " "
  }
}