{
  "source_id": "cbsl",
  "category": "Health-Personel",
  "sub_category": "No.of Radiographers",
  "scale": " ",
  "unit": "Number",
  "frequency_name": "Annual",
  "i_subject": 8,
  "footnotes": {
    "Sector": "Real Sector",
    "Source": "Medical Statistics Unit, Ministry of Health",
    "GeoArea": "National",
    "Note": "",
    "Data last updated": "2023-01-12",
    "Update frequency": "End of August"
  },
  "summary_statistics": {
    "n": 18,
    "min_t": "2000-01-01",
    "max_t": "2019-01-01",
    "min_value": 290,
    "max_value": 0
  },
  "cleaned_data": {
    "2000-01-01": 290,
    "2001-01-01": 335,
    "2002-01-01": 371,
    "2003-01-01": 342,
    "2004-01-01": 332,
    "2005-01-01": 350,
    "2007-01-01": 392,
    "2008-01-01": 444,
    "2009-01-01": 464,
    "2010-01-01": 542,
    "2012-01-01": 588,
    "2013-01-01": 578,
    "2014-01-01": 649,
    "2015-01-01": 588,
    "2016-01-01": 607,
    "2017-01-01": 610,
    "2018-01-01": 632,
    "2019-01-01": 0
  },
  "raw_data": {
    "1964": " ",
    "1965": " ",
    "1966": " ",
    "1967": " ",
    "1968": " ",
    "1969": " ",
    "1970": " ",
    "1971": " ",
    "1972": " ",
    "1973": " ",
    "1974": " ",
    "1975": " ",
    "1976": " ",
    "1977": " ",
    "1978": " ",
    "1979": " ",
    "1980": " ",
    "1981": " ",
    "1982": " ",
    "1983": " ",
    "1984": " ",
    "1985": " ",
    "1986": " ",
    "1987": " ",
    "1988": " ",
    "1989": " ",
    "1990": " ",
    "1991": " ",
    "1992": " ",
    "1993": " ",
    "1994": " ",
    "1995": " ",
    "1996": " ",
    "1997": " ",
    "1998": " ",
    "1999": " ",
    "2000": "290",
    "2001": "335",
    "2002": "371",
    "2003": "342",
    "2004": "332",
    "2005": "350",
    "2006": "n.a.",
    "2007": "392",
    "2008": "444",
    "2009": "464",
    "2010": "542",
    "2011": "n.a.",
    "2012": "588",
    "2013": "578",
    "2014": "649",
    "2015": "588",
    "2016": "607",
    "2017": "610",
    "2018": "632",
    "2019": "-",
    "2020": " ",
    "2021": " ",
    "2022": " ",
    "2023": " ",
    "2024": " "
  }
}