{
  "source_id": "cbsl",
  "category": "Agriculture-Tea",
  "sub_category": "No. of Tea Factories - Sabaragamuwa",
  "scale": " ",
  "unit": "Number",
  "frequency_name": "Annual",
  "i_subject": 2,
  "footnotes": {
    "Sector": "Real Sector",
    "Source": "Sri Lanka Tea Board",
    "GeoArea": "Provincial",
    "Note": "No. of Tea Factories (in operation)",
    "Data last updated": "2023-01-11",
    "Update frequency": "End of August"
  },
  "summary_statistics": {
    "n": 17,
    "min_t": "2005-01-01",
    "max_t": "2021-01-01",
    "min_value": 123.0,
    "max_value": 119
  },
  "cleaned_data": {
    "2005-01-01": 123.0,
    "2006-01-01": 112.0,
    "2007-01-01": 111.0,
    "2008-01-01": 113.0,
    "2009-01-01": 107.0,
    "2010-01-01": 131.0,
    "2011-01-01": 139.0,
    "2012-01-01": 119.0,
    "2013-01-01": 142.0,
    "2014-01-01": 140,
    "2015-01-01": 141,
    "2016-01-01": 138,
    "2017-01-01": 140,
    "2018-01-01": 140.0,
    "2019-01-01": 140,
    "2020-01-01": 121.0,
    "2021-01-01": 119
  },
  "raw_data": {
    "1965": " ",
    "1966": " ",
    "1967": " ",
    "1968": " ",
    "1969": " ",
    "1970": " ",
    "1971": " ",
    "1972": " ",
    "1973": " ",
    "1974": " ",
    "1975": " ",
    "1976": " ",
    "1977": " ",
    "1978": " ",
    "1979": " ",
    "1980": " ",
    "1981": " ",
    "1982": " ",
    "1983": " ",
    "1984": " ",
    "1985": " ",
    "1986": " ",
    "1987": " ",
    "1988": " ",
    "1989": " ",
    "1990": " ",
    "1991": " ",
    "1992": " ",
    "1993": " ",
    "1994": " ",
    "1995": " ",
    "1996": " ",
    "1997": " ",
    "1998": " ",
    "1999": " ",
    "2000": " ",
    "2001": " ",
    "2002": " ",
    "2003": " ",
    "2004": " ",
    "2005": "123.00",
    "2006": "112.00",
    "2007": "111.00",
    "2008": "113.00",
    "2009": "107.00",
    "2010": "131.00",
    "2011": "139.00",
    "2012": "119.00",
    "2013": "142.00",
    "2014": "140",
    "2015": "141",
    "2016": "138",
    "2017": "140",
    "2018": "140.00",
    "2019": "140",
    "2020": "121.00",
    "2021": "119",
    "2022": " ",
    "2023": " ",
    "2024": " ",
    "2025": " "
  }
}