{
  "source_id": "cbsl",
  "category": "Revenue and Expenditure of Provincial Councils-Expenditure of Provincial Councils",
  "sub_category": "Revenue and Expenditure of Provincial Councils-Expenditure-Capital Expenditure-Western",
  "scale": "Mn.",
  "unit": "Rs.",
  "frequency_name": "Annual",
  "i_subject": 31,
  "footnotes": {
    "Sector": "Real Sector",
    "Source": "Ministry of Local Government and Provincial Councils",
    "GeoArea": "Provincial",
    "Note": "As at end December.",
    "Data last updated": "2023-01-11",
    "Update frequency": "End of August"
  },
  "summary_statistics": {
    "n": 22,
    "min_t": "1999-01-01",
    "max_t": "2021-01-01",
    "min_value": 737,
    "max_value": 608
  },
  "cleaned_data": {
    "1999-01-01": 737,
    "2000-01-01": 483,
    "2002-01-01": 392,
    "2003-01-01": 1021,
    "2004-01-01": 538,
    "2005-01-01": 868,
    "2006-01-01": 639,
    "2007-01-01": 824,
    "2008-01-01": 1065,
    "2009-01-01": 3310,
    "2010-01-01": 1451,
    "2011-01-01": 2940,
    "2012-01-01": 6065,
    "2013-01-01": 6062,
    "2014-01-01": 6986,
    "2015-01-01": 4654,
    "2016-01-01": 6218,
    "2017-01-01": 7158,
    "2018-01-01": 10898.0,
    "2019-01-01": 111,
    "2020-01-01": 99.0,
    "2021-01-01": 608
  },
  "raw_data": {
    "1965": " ",
    "1966": " ",
    "1967": " ",
    "1968": " ",
    "1969": " ",
    "1970": " ",
    "1971": " ",
    "1972": " ",
    "1973": " ",
    "1974": " ",
    "1975": " ",
    "1976": " ",
    "1977": " ",
    "1978": " ",
    "1979": " ",
    "1980": " ",
    "1981": " ",
    "1982": " ",
    "1983": " ",
    "1984": " ",
    "1985": " ",
    "1986": " ",
    "1987": " ",
    "1988": " ",
    "1989": " ",
    "1990": " ",
    "1991": " ",
    "1992": " ",
    "1993": " ",
    "1994": " ",
    "1995": " ",
    "1996": " ",
    "1997": " ",
    "1998": " ",
    "1999": "737",
    "2000": "483",
    "2001": "n.a.",
    "2002": "392",
    "2003": "1,021",
    "2004": "538",
    "2005": "868",
    "2006": "639",
    "2007": "824",
    "2008": "1,065",
    "2009": "3,310",
    "2010": "1,451",
    "2011": "2,940",
    "2012": "6,065",
    "2013": "6,062",
    "2014": "6,986",
    "2015": "4,654",
    "2016": "6,218",
    "2017": "7,158",
    "2018": "10,898.00",
    "2019": "111",
    "2020": "99.00",
    "2021": "608",
    "2022": " ",
    "2023": " ",
    "2024": " ",
    "2025": " "
  }
}