{
  "source_id": "cbsl",
  "category": "Revenue and Expenditure of Provincial Councils-Expenditure of Provincial Councils",
  "sub_category": "Revenue and Expenditure of Provincial Councils-Expenditures-Total-Southern",
  "scale": "Mn.",
  "unit": "Rs.",
  "frequency_name": "Annual",
  "i_subject": 31,
  "footnotes": {
    "Sector": "Real Sector",
    "Source": "Ministry of Local Government and Provincial Councils",
    "GeoArea": "Provincial",
    "Note": "As at end December.",
    "Data last updated": "2023-01-11",
    "Update frequency": "End of August"
  },
  "summary_statistics": {
    "n": 22,
    "min_t": "1999-01-01",
    "max_t": "2021-01-01",
    "min_value": 4423,
    "max_value": 42822
  },
  "cleaned_data": {
    "1999-01-01": 4423,
    "2000-01-01": 4147,
    "2002-01-01": 4642,
    "2003-01-01": 5612,
    "2004-01-01": 6189,
    "2005-01-01": 7750,
    "2006-01-01": 9913,
    "2007-01-01": 12251,
    "2008-01-01": 11229,
    "2009-01-01": 14613,
    "2010-01-01": 15504,
    "2011-01-01": 17720,
    "2012-01-01": 17780,
    "2013-01-01": 19158,
    "2014-01-01": 22115,
    "2015-01-01": 27662,
    "2016-01-01": 31698,
    "2017-01-01": 32978,
    "2018-01-01": 34632.0,
    "2019-01-01": 35510,
    "2020-01-01": 39790.0,
    "2021-01-01": 42822
  },
  "raw_data": {
    "1965": " ",
    "1966": " ",
    "1967": " ",
    "1968": " ",
    "1969": " ",
    "1970": " ",
    "1971": " ",
    "1972": " ",
    "1973": " ",
    "1974": " ",
    "1975": " ",
    "1976": " ",
    "1977": " ",
    "1978": " ",
    "1979": " ",
    "1980": " ",
    "1981": " ",
    "1982": " ",
    "1983": " ",
    "1984": " ",
    "1985": " ",
    "1986": " ",
    "1987": " ",
    "1988": " ",
    "1989": " ",
    "1990": " ",
    "1991": " ",
    "1992": " ",
    "1993": " ",
    "1994": " ",
    "1995": " ",
    "1996": " ",
    "1997": " ",
    "1998": " ",
    "1999": "4,423",
    "2000": "4,147",
    "2001": "n.a.",
    "2002": "4,642",
    "2003": "5,612",
    "2004": "6,189",
    "2005": "7,750",
    "2006": "9,913",
    "2007": "12,251",
    "2008": "11,229",
    "2009": "14,613",
    "2010": "15,504",
    "2011": "17,720",
    "2012": "17,780",
    "2013": "19,158",
    "2014": "22,115",
    "2015": "27,662",
    "2016": "31,698",
    "2017": "32,978",
    "2018": "34,632.00",
    "2019": "35,510",
    "2020": "39,790.00",
    "2021": "42,822",
    "2022": " ",
    "2023": " ",
    "2024": " ",
    "2025": " "
  }
}