{
  "source_id": "cbsl",
  "category": "Banking Sector-Licensed Specialised Banks",
  "sub_category": "Licensed Specialised Banks- Non-interest Income",
  "scale": "Millions",
  "unit": "Rs",
  "frequency_name": "Annual",
  "i_subject": 24,
  "footnotes": {
    "Sector": "Financial",
    "Source": "CBSL Website",
    "GeoArea": "National",
    "Note": "",
    "Data last updated": "2021-03-05",
    "Update frequency": "10th day of next second month of next year"
  },
  "summary_statistics": {
    "n": 23,
    "min_t": "1998-01-01",
    "max_t": "2020-01-01",
    "min_value": 799,
    "max_value": 6714
  },
  "cleaned_data": {
    "1998-01-01": 799,
    "1999-01-01": 1160,
    "2000-01-01": 1400,
    "2001-01-01": 1424,
    "2002-01-01": 2347,
    "2003-01-01": 2647,
    "2004-01-01": 2200,
    "2005-01-01": 2190,
    "2006-01-01": 1537,
    "2007-01-01": 3977,
    "2008-01-01": 7990,
    "2009-01-01": 9812,
    "2010-01-01": 15538,
    "2011-01-01": 6978,
    "2012-01-01": 7160,
    "2013-01-01": 8801,
    "2014-01-01": 12072,
    "2015-01-01": 5781,
    "2016-01-01": 5334,
    "2017-01-01": 9013,
    "2018-01-01": 6532,
    "2019-01-01": 5256,
    "2020-01-01": 6714
  },
  "raw_data": {
    "1965": " ",
    "1966": " ",
    "1967": " ",
    "1968": " ",
    "1969": " ",
    "1970": " ",
    "1971": " ",
    "1972": " ",
    "1973": " ",
    "1974": " ",
    "1975": " ",
    "1976": " ",
    "1977": " ",
    "1978": " ",
    "1979": " ",
    "1980": " ",
    "1981": " ",
    "1982": " ",
    "1983": " ",
    "1984": " ",
    "1985": " ",
    "1986": " ",
    "1987": " ",
    "1988": " ",
    "1989": " ",
    "1990": " ",
    "1991": " ",
    "1992": " ",
    "1993": " ",
    "1994": " ",
    "1995": " ",
    "1996": " ",
    "1997": " ",
    "1998": "799",
    "1999": "1,160",
    "2000": "1,400",
    "2001": "1,424",
    "2002": "2,347",
    "2003": "2,647",
    "2004": "2,200",
    "2005": "2,190",
    "2006": "1,537",
    "2007": "3,977",
    "2008": "7,990",
    "2009": "9,812",
    "2010": "15,538",
    "2011": "6,978",
    "2012": "7,160",
    "2013": "8,801",
    "2014": "12,072",
    "2015": "5,781",
    "2016": "5,334",
    "2017": "9,013",
    "2018": "6,532",
    "2019": "5,256",
    "2020": "6,714",
    "2021": " ",
    "2022": " ",
    "2023": " ",
    "2024": " ",
    "2025": " "
  }
}