{
  "source_id": "cbsl",
  "category": "Agriculture-Paddy",
  "sub_category": "Paddy Yield - Bushels per Acre - Central",
  "scale": " ",
  "unit": "Bushels per Acre",
  "frequency_name": "Annual",
  "i_subject": 2,
  "footnotes": {
    "Sector": "Real Sector",
    "Source": "Department of Census and Statistics",
    "GeoArea": "Provincial",
    "Note": "",
    "Data last updated": "2023-01-12",
    "Update frequency": "End of August"
  },
  "summary_statistics": {
    "n": 17,
    "min_t": "2005-01-01",
    "max_t": "2021-01-01",
    "min_value": 71,
    "max_value": 76
  },
  "cleaned_data": {
    "2005-01-01": 71,
    "2006-01-01": 70,
    "2007-01-01": 74,
    "2008-01-01": 72,
    "2009-01-01": 72,
    "2010-01-01": 79,
    "2011-01-01": 71,
    "2012-01-01": 80,
    "2013-01-01": 83,
    "2014-01-01": 78,
    "2015-01-01": 82,
    "2016-01-01": 81,
    "2017-01-01": 83,
    "2018-01-01": 84.0,
    "2019-01-01": 92,
    "2020-01-01": 93.0,
    "2021-01-01": 76
  },
  "raw_data": {
    "1965": " ",
    "1966": " ",
    "1967": " ",
    "1968": " ",
    "1969": " ",
    "1970": " ",
    "1971": " ",
    "1972": " ",
    "1973": " ",
    "1974": " ",
    "1975": " ",
    "1976": " ",
    "1977": " ",
    "1978": " ",
    "1979": " ",
    "1980": " ",
    "1981": " ",
    "1982": " ",
    "1983": " ",
    "1984": " ",
    "1985": " ",
    "1986": " ",
    "1987": " ",
    "1988": " ",
    "1989": " ",
    "1990": " ",
    "1991": " ",
    "1992": " ",
    "1993": " ",
    "1994": " ",
    "1995": " ",
    "1996": " ",
    "1997": " ",
    "1998": " ",
    "1999": " ",
    "2000": " ",
    "2001": " ",
    "2002": " ",
    "2003": " ",
    "2004": " ",
    "2005": "71",
    "2006": "70",
    "2007": "74",
    "2008": "72",
    "2009": "72",
    "2010": "79",
    "2011": "71",
    "2012": "80",
    "2013": "83",
    "2014": "78",
    "2015": "82",
    "2016": "81",
    "2017": "83",
    "2018": "84.00",
    "2019": "92",
    "2020": "93.00",
    "2021": "76",
    "2022": " ",
    "2023": " ",
    "2024": " ",
    "2025": " "
  }
}