{
  "source_id": "cbsl",
  "category": "Industry and Housing-Electricity Sales",
  "sub_category": "Electricity Sales-No. of Consumer Accounts-Sabaragamuwa-Total",
  "scale": " ",
  "unit": "Number",
  "frequency_name": "Annual",
  "i_subject": 3,
  "footnotes": {
    "Sector": "Real Sector",
    "Source": "Ceylon Electricity Board",
    "GeoArea": "Provincial",
    "Note": "",
    "Data last updated": "2023-01-05",
    "Update frequency": "End of August"
  },
  "summary_statistics": {
    "n": 23,
    "min_t": "1999-01-01",
    "max_t": "2021-01-01",
    "min_value": 202798,
    "max_value": 505046
  },
  "cleaned_data": {
    "1999-01-01": 202798,
    "2000-01-01": 228128,
    "2001-01-01": 246828,
    "2002-01-01": 261047,
    "2003-01-01": 277354,
    "2004-01-01": 295400,
    "2005-01-01": 314415,
    "2006-01-01": 284147,
    "2007-01-01": 306927,
    "2008-01-01": 329254,
    "2009-01-01": 350073,
    "2010-01-01": 374729,
    "2011-01-01": 403359,
    "2012-01-01": 433969,
    "2013-01-01": 390039,
    "2014-01-01": 405847,
    "2015-01-01": 428649,
    "2016-01-01": 447709,
    "2017-01-01": 464726,
    "2018-01-01": 475925.0,
    "2019-01-01": 485231,
    "2020-01-01": 493033.0,
    "2021-01-01": 505046
  },
  "raw_data": {
    "1965": " ",
    "1966": " ",
    "1967": " ",
    "1968": " ",
    "1969": " ",
    "1970": " ",
    "1971": " ",
    "1972": " ",
    "1973": " ",
    "1974": " ",
    "1975": " ",
    "1976": " ",
    "1977": " ",
    "1978": " ",
    "1979": " ",
    "1980": " ",
    "1981": " ",
    "1982": " ",
    "1983": " ",
    "1984": " ",
    "1985": " ",
    "1986": " ",
    "1987": " ",
    "1988": " ",
    "1989": " ",
    "1990": " ",
    "1991": " ",
    "1992": " ",
    "1993": " ",
    "1994": " ",
    "1995": " ",
    "1996": " ",
    "1997": " ",
    "1998": " ",
    "1999": "202,798",
    "2000": "228,128",
    "2001": "246,828",
    "2002": "261,047",
    "2003": "277,354",
    "2004": "295,400",
    "2005": "314,415",
    "2006": "284,147",
    "2007": "306,927",
    "2008": "329,254",
    "2009": "350,073",
    "2010": "374,729",
    "2011": "403,359",
    "2012": "433,969",
    "2013": "390,039",
    "2014": "405,847",
    "2015": "428,649",
    "2016": "447,709",
    "2017": "464,726",
    "2018": "475,925.00",
    "2019": "485,231",
    "2020": "493,033.00",
    "2021": "505,046",
    "2022": " ",
    "2023": " ",
    "2024": " ",
    "2025": " "
  }
}