{
  "source_id": "cbsl",
  "category": "Transport-Motor Vehicles",
  "sub_category": "Motor Vehicles by Province-Goods Transport Vehicles-Central",
  "scale": " ",
  "unit": "Number",
  "frequency_name": "Annual",
  "i_subject": 10,
  "footnotes": {
    "Sector": "Real Sector",
    "Source": "Divisional Secretariats",
    "GeoArea": "Provincial",
    "Note": "Motor Vehicles with valid revenue licenses",
    "Data last updated": "2023-01-11",
    "Update frequency": "End of August"
  },
  "summary_statistics": {
    "n": 23,
    "min_t": "1999-01-01",
    "max_t": "2021-01-01",
    "min_value": 8432,
    "max_value": 24645
  },
  "cleaned_data": {
    "1999-01-01": 8432,
    "2000-01-01": 8852,
    "2001-01-01": 14919,
    "2002-01-01": 14819,
    "2003-01-01": 14534,
    "2004-01-01": 14878,
    "2005-01-01": 16275,
    "2006-01-01": 17774,
    "2007-01-01": 19244,
    "2008-01-01": 20111,
    "2009-01-01": 20741,
    "2010-01-01": 4607,
    "2011-01-01": 21057,
    "2012-01-01": 22491,
    "2013-01-01": 22331,
    "2014-01-01": 20314,
    "2015-01-01": 21005,
    "2016-01-01": 22816,
    "2017-01-01": 24501,
    "2018-01-01": 24812.0,
    "2019-01-01": 24048,
    "2020-01-01": 24814,
    "2021-01-01": 24645
  },
  "raw_data": {
    "1965": " ",
    "1966": " ",
    "1967": " ",
    "1968": " ",
    "1969": " ",
    "1970": " ",
    "1971": " ",
    "1972": " ",
    "1973": " ",
    "1974": " ",
    "1975": " ",
    "1976": " ",
    "1977": " ",
    "1978": " ",
    "1979": " ",
    "1980": " ",
    "1981": " ",
    "1982": " ",
    "1983": " ",
    "1984": " ",
    "1985": " ",
    "1986": " ",
    "1987": " ",
    "1988": " ",
    "1989": " ",
    "1990": " ",
    "1991": " ",
    "1992": " ",
    "1993": " ",
    "1994": " ",
    "1995": " ",
    "1996": " ",
    "1997": " ",
    "1998": " ",
    "1999": "8,432",
    "2000": "8,852",
    "2001": "14,919",
    "2002": "14,819",
    "2003": "14,534",
    "2004": "14,878",
    "2005": "16,275",
    "2006": "17,774",
    "2007": "19,244",
    "2008": "20,111",
    "2009": "20,741",
    "2010": "4,607",
    "2011": "21,057",
    "2012": "22,491",
    "2013": "22,331",
    "2014": "20,314",
    "2015": "21,005",
    "2016": "22,816",
    "2017": "24,501",
    "2018": "24,812.00",
    "2019": "24,048",
    "2020": "24,814",
    "2021": "24,645",
    "2022": " ",
    "2023": " ",
    "2024": " ",
    "2025": " "
  }
}