{
  "source_id": "cbsl",
  "category": "Agriculture-National Livestock Statistics",
  "sub_category": "National Milk Production",
  "scale": "Million",
  "unit": "Mn litres",
  "frequency_name": "Annual",
  "i_subject": 2,
  "footnotes": {
    "Sector": "Real Sector",
    "Source": "Department of Animal Production and Health / Department of Census and Statistics",
    "GeoArea": "National",
    "Note": "",
    "Data last updated": "2022-04-25",
    "Update frequency": "Four Months after end of the year and halfyear"
  },
  "summary_statistics": {
    "n": 25,
    "min_t": "1997-01-01",
    "max_t": "2021-01-01",
    "min_value": 77.06,
    "max_value": 513.31
  },
  "cleaned_data": {
    "1997-01-01": 77.06,
    "1998-01-01": 79.94,
    "1999-01-01": 82.28,
    "2000-01-01": 85.19,
    "2001-01-01": 81.6,
    "2002-01-01": 81.13,
    "2003-01-01": 83.87,
    "2004-01-01": 83.73,
    "2005-01-01": 82.08,
    "2006-01-01": 88.51,
    "2007-01-01": 92.48,
    "2008-01-01": 99.25,
    "2009-01-01": 99.56,
    "2010-01-01": 108.71,
    "2011-01-01": 111.11,
    "2012-01-01": 116.82,
    "2013-01-01": 121.87,
    "2014-01-01": 119.88,
    "2015-01-01": 374.4,
    "2016-01-01": 384.0,
    "2017-01-01": 396.2,
    "2018-01-01": 471.6,
    "2019-01-01": 447.6,
    "2020-01-01": 491.54,
    "2021-01-01": 513.31
  },
  "raw_data": {
    "1965": " ",
    "1966": " ",
    "1967": " ",
    "1968": " ",
    "1969": " ",
    "1970": " ",
    "1971": " ",
    "1972": " ",
    "1973": " ",
    "1974": " ",
    "1975": " ",
    "1976": " ",
    "1977": " ",
    "1978": " ",
    "1979": " ",
    "1980": " ",
    "1981": " ",
    "1982": " ",
    "1983": " ",
    "1984": " ",
    "1985": " ",
    "1986": " ",
    "1987": " ",
    "1988": " ",
    "1989": " ",
    "1990": " ",
    "1991": " ",
    "1992": " ",
    "1993": " ",
    "1994": " ",
    "1995": " ",
    "1996": " ",
    "1997": "77.06",
    "1998": "79.94",
    "1999": "82.28",
    "2000": "85.19",
    "2001": "81.60",
    "2002": "81.13",
    "2003": "83.87",
    "2004": "83.73",
    "2005": "82.08",
    "2006": "88.51",
    "2007": "92.48",
    "2008": "99.25",
    "2009": "99.56",
    "2010": "108.71",
    "2011": "111.11",
    "2012": "116.82",
    "2013": "121.87",
    "2014": "119.88",
    "2015": "374.40",
    "2016": "384.00",
    "2017": "396.20",
    "2018": "471.60",
    "2019": "447.60",
    "2020": "491.54",
    "2021": "513.31",
    "2022": " ",
    "2023": " ",
    "2024": " ",
    "2025": " "
  }
}