{
  "source_id": "cbsl",
  "category": "National Accounts-GDP at Current Prices - Base Year 2002",
  "sub_category": "GDP - Exp. at Current MP (2002 Series) - Consumption - PCE - Hotels Cafes and Restaurants",
  "scale": "Million",
  "unit": "Rs.",
  "frequency_name": "Annual",
  "i_subject": 1,
  "footnotes": {},
  "summary_statistics": {
    "n": 13,
    "min_t": "2002-01-01",
    "max_t": "2014-01-01",
    "min_value": 20682.0,
    "max_value": 150433.0
  },
  "cleaned_data": {
    "2002-01-01": 20682.0,
    "2003-01-01": 24568.0,
    "2004-01-01": 26422.0,
    "2005-01-01": 29567.9,
    "2006-01-01": 35798.37,
    "2007-01-01": 38630.0,
    "2008-01-01": 45350.0,
    "2009-01-01": 46749.0,
    "2010-01-01": 48478.0,
    "2011-01-01": 58336.0,
    "2012-01-01": 87786.0,
    "2013-01-01": 113720.29,
    "2014-01-01": 150433.0
  },
  "raw_data": {
    "1965": " ",
    "1966": " ",
    "1967": " ",
    "1968": " ",
    "1969": " ",
    "1970": " ",
    "1971": " ",
    "1972": " ",
    "1973": " ",
    "1974": " ",
    "1975": " ",
    "1976": " ",
    "1977": " ",
    "1978": " ",
    "1979": " ",
    "1980": " ",
    "1981": " ",
    "1982": " ",
    "1983": " ",
    "1984": " ",
    "1985": " ",
    "1986": " ",
    "1987": " ",
    "1988": " ",
    "1989": " ",
    "1990": " ",
    "1991": " ",
    "1992": " ",
    "1993": " ",
    "1994": " ",
    "1995": " ",
    "1996": " ",
    "1997": " ",
    "1998": " ",
    "1999": " ",
    "2000": " ",
    "2001": " ",
    "2002": "20,682.00",
    "2003": "24,568.00",
    "2004": "26,422.00",
    "2005": "29,567.90",
    "2006": "35,798.37",
    "2007": "38,630.00",
    "2008": "45,350.00",
    "2009": "46,749.00",
    "2010": "48,478.00",
    "2011": "58,336.00",
    "2012": "87,786.00",
    "2013": "113,720.29",
    "2014": "150,433.00",
    "2015": " ",
    "2016": " ",
    "2017": " ",
    "2018": " ",
    "2019": " ",
    "2020": " ",
    "2021": " ",
    "2022": " ",
    "2023": " ",
    "2024": " ",
    "2025": " "
  }
}