{
  "unit": "Rs.",
  "scale": "Million",
  "data": {
    "1990": " ",
    "1991": " ",
    "1992": " ",
    "1993": " ",
    "1994": " ",
    "1995": " ",
    "1996": " ",
    "1997": " ",
    "1998": " ",
    "1999": " ",
    "2000": " ",
    "2001": " ",
    "2002": "18,539.00",
    "2003": "19,490.00",
    "2004": "20,601.00",
    "2005": "21,907.00",
    "2006": "23,165.72",
    "2007": "24,472.16",
    "2008": "25,569.74",
    "2009": "26,411.86",
    "2010": "27,867.55",
    "2011": "29,807.76",
    "2012": "31,173.90",
    "2013": "32,763.99",
    "2014": "33,599.00",
    "2015": "34,886",
    "2016": " ",
    "2017": " ",
    "2018": " ",
    "2019": " ",
    "2020": " ",
    "2021": " ",
    "2022": " ",
    "2023": " "
  }
}