{
  "source_id": "imf",
  "category": "IMF - Sri Lanka Data",
  "sub_category": "Nominal GDP",
  "scale": "",
  "unit": "Millions of US Dollars",
  "frequency_name": "Annual",
  "i_subject": -1,
  "footnotes": {
    "indicator_key": "GDP",
    "description": null,
    "source": "Capital Flows in Developing Economies",
    "dataset": "CF",
    "url": "https://www.imf.org/external/datamapper/api/v1/GDP/LKA"
  },
  "summary_statistics": {
    "n": 20,
    "min_t": "1995",
    "max_t": "2014",
    "min_value": 12787.3,
    "max_value": 74923.78
  },
  "cleaned_data": {
    "1995": 12787.3,
    "1996": 14025.11,
    "1997": 15630.14,
    "1998": 16103.41,
    "1999": 16192.5,
    "2000": 16925.84,
    "2001": 16260.77,
    "2002": 17112.6,
    "2003": 18891.85,
    "2004": 20669.51,
    "2005": 24418,
    "2006": 28274.35,
    "2007": 32367.16,
    "2008": 40719.84,
    "2009": 42039.61,
    "2010": 49551.9,
    "2011": 59157.42,
    "2012": 59378.25,
    "2013": 67451.07,
    "2014": 74923.78
  },
  "raw_data": {
    "1995": 12787.3,
    "1996": 14025.11,
    "1997": 15630.14,
    "1998": 16103.41,
    "1999": 16192.5,
    "2000": 16925.84,
    "2001": 16260.77,
    "2002": 17112.6,
    "2003": 18891.85,
    "2004": 20669.51,
    "2005": 24418,
    "2006": 28274.35,
    "2007": 32367.16,
    "2008": 40719.84,
    "2009": 42039.61,
    "2010": 49551.9,
    "2011": 59157.42,
    "2012": 59378.25,
    "2013": 67451.07,
    "2014": 74923.78
  }
}