{
  "unit": "Kg",
  "scale": "Million",
  "data": {
    "1984": " ",
    "1985": " ",
    "1986": " ",
    "1987": " ",
    "1988": " ",
    "1989": " ",
    "1990": " ",
    "1991": " ",
    "1992": " ",
    "1993": " ",
    "1994": " ",
    "1995": " ",
    "1996": " ",
    "1997": "60.57",
    "1998": "54.30",
    "1999": "56.59",
    "2000": "62.31",
    "2001": "58.53",
    "2002": "59.58",
    "2003": "63.83",
    "2004": "67.96",
    "2005": "79.21",
    "2006": "73.31",
    "2007": "86.91",
    "2008": "87.70",
    "2009": "107.32",
    "2010": "108.90",
    "2011": "118.62",
    "2012": "102.80",
    "2013": "115.11",
    "2014": "116.50",
    "2015": "105.88",
    "2016": "98.30",
    "2017": "82.93",
    "2018": "123.26",
    "2019": "97.47",
    "2020": "113.32",
    "2021": "112.14",
    "2022": " ",
    "2023": " ",
    "2024": " "
  }
}