{
  "unit": "Kg",
  "scale": "Million",
  "data": {
    "1984": " ",
    "1985": " ",
    "1986": " ",
    "1987": " ",
    "1988": " ",
    "1989": " ",
    "1990": " ",
    "1991": " ",
    "1992": " ",
    "1993": " ",
    "1994": " ",
    "1995": " ",
    "1996": " ",
    "1997": " ",
    "1998": " ",
    "1999": " ",
    "2000": " ",
    "2001": " ",
    "2002": " ",
    "2003": " ",
    "2004": " ",
    "2005": " ",
    "2006": " ",
    "2007": " ",
    "2008": " ",
    "2009": " ",
    "2010": "12.05",
    "2011": "13.66",
    "2012": "14.91",
    "2013": "14.08",
    "2014": "15.48",
    "2015": "17.27",
    "2016": "23.18",
    "2017": "16.33",
    "2018": "14.21",
    "2019": "15.69",
    "2020": "42.01",
    "2021": "56.83",
    "2022": " ",
    "2023": " ",
    "2024": " "
  }
}