{
  "unit": "Unit",
  "scale": "Unit",
  "data": {
    "1984": " ",
    "1985": " ",
    "1986": " ",
    "1987": " ",
    "1988": " ",
    "1989": " ",
    "1990": " ",
    "1991": " ",
    "1992": " ",
    "1993": " ",
    "1994": " ",
    "1995": " ",
    "1996": " ",
    "1997": " ",
    "1998": " ",
    "1999": " ",
    "2000": " ",
    "2001": " ",
    "2002": " ",
    "2003": " ",
    "2004": " ",
    "2005": " ",
    "2006": " ",
    "2007": " ",
    "2008": "118",
    "2009": "119",
    "2010": "126",
    "2011": "136",
    "2012": "139",
    "2013": "142",
    "2014": "150",
    "2015": "151",
    "2016": "152",
    "2017": "156",
    "2018": "160",
    "2019": "161",
    "2020": "163",
    "2021": " ",
    "2022": " ",
    "2023": " ",
    "2024": " "
  }
}