{
  "unit": "Rs.",
  "scale": "Mn.",
  "data": {
    "1984": " ",
    "1985": " ",
    "1986": " ",
    "1987": " ",
    "1988": " ",
    "1989": " ",
    "1990": " ",
    "1991": " ",
    "1992": " ",
    "1993": " ",
    "1994": " ",
    "1995": " ",
    "1996": " ",
    "1997": " ",
    "1998": " ",
    "1999": "4,029",
    "2000": "2,550",
    "2001": "n.a.",
    "2002": "2,764",
    "2003": "3,583",
    "2004": "4,015",
    "2005": "5,285",
    "2006": "5,857",
    "2007": "7,022",
    "2008": "10,039",
    "2009": "9,971",
    "2010": "11,095",
    "2011": "10,941",
    "2012": "11,976",
    "2013": "12,682",
    "2014": "17,152",
    "2015": "20,689",
    "2016": "21,234",
    "2017": "22,327",
    "2018": "22,358.00",
    "2019": "23,784",
    "2020": "27,231.00",
    "2021": "29,527",
    "2022": " ",
    "2023": " ",
    "2024": " "
  }
}