{
  "unit": "USD",
  "scale": "Millions",
  "data": {
    "1984": " ",
    "1985": " ",
    "1986": " ",
    "1987": " ",
    "1988": " ",
    "1989": " ",
    "1990": " ",
    "1991": " ",
    "1992": " ",
    "1993": " ",
    "1994": "239.70",
    "1995": "51.50",
    "1996": "-67.80",
    "1997": "162.70",
    "1998": "36.70",
    "1999": "-252.30",
    "2000": "-521.90",
    "2001": "188.60",
    "2002": "338.00",
    "2003": "502.40",
    "2004": "-205.30",
    "2005": "501.60",
    "2006": "203.50",
    "2007": "530.60",
    "2008": "-1,225.40",
    "2009": "2,566.00",
    "2010": "921.20",
    "2011": "-1,059.40",
    "2012": "151.20",
    "2013": "985.40",
    "2014": "1,368.90",
    "2015": "-1,488.73",
    "2016": "-499.77",
    "2017": "2,068.45",
    "2018": "-1,102.86",
    "2019": "376.56",
    "2020": "-2,327.69",
    "2021": " ",
    "2022": " ",
    "2023": " ",
    "2024": " "
  }
}