{
  "unit": "Rs.",
  "scale": "Million",
  "data": {
    "1964": " ",
    "1965": " ",
    "1966": " ",
    "1967": " ",
    "1968": " ",
    "1969": " ",
    "1970": " ",
    "1971": " ",
    "1972": " ",
    "1973": " ",
    "1974": " ",
    "1975": " ",
    "1976": " ",
    "1977": " ",
    "1978": " ",
    "1979": " ",
    "1980": " ",
    "1981": " ",
    "1982": " ",
    "1983": " ",
    "1984": " ",
    "1985": " ",
    "1986": " ",
    "1987": " ",
    "1988": " ",
    "1989": " ",
    "1990": " ",
    "1991": " ",
    "1992": " ",
    "1993": " ",
    "1994": " ",
    "1995": " ",
    "1996": " ",
    "1997": " ",
    "1998": " ",
    "1999": " ",
    "2000": " ",
    "2001": " ",
    "2002": "1,672.00",
    "2003": "1,807.00",
    "2004": "1,886.50",
    "2005": "2,022.93",
    "2006": "2,210.12",
    "2007": "2,484.00",
    "2008": "2,820.00",
    "2009": "3,116.00",
    "2010": "12,495.00",
    "2011": "15,265.00",
    "2012": "19,245.30",
    "2013": "24,375.87",
    "2014": "31,716.00",
    "2015": " ",
    "2016": " ",
    "2017": " ",
    "2018": " ",
    "2019": " ",
    "2020": " ",
    "2021": " ",
    "2022": " ",
    "2023": " ",
    "2024": " "
  }
}