{
  "source_id": "adb",
  "category": "",
  "sub_category": "Expenditure on GDP at 1998 _ 2002 _ 2010 market pricesj - Statistical discrepancy - Acquisitions less disposals of valuables - Exports of goods and services",
  "scale": "",
  "unit": "",
  "frequency_name": "Annual",
  "i_subject": -1,
  "footnotes": {},
  "summary_statistics": {
    "n": 20,
    "min_t": 2000,
    "max_t": 2021,
    "min_value": 17.10014,
    "max_value": 16.968385150298
  },
  "cleaned_data": {
    "2000": 17.10014,
    "2001": -8.00001,
    "2003": 3.3563,
    "2004": 7.7435,
    "2005": 6.64617,
    "2006": 3.84046,
    "2007": 7.32729,
    "2008": 0.39012,
    "2009": -12.3057,
    "2011": 10.2,
    "2012": -0.2,
    "2013": 6.6,
    "2014": 4.3,
    "2015": 4.7,
    "2016": -0.7,
    "2017": 7.6,
    "2018": 0.5,
    "2019": 7.16558041,
    "2020": -9.580773761,
    "2021": 16.968385150298
  },
  "raw_data": {
    "2000": 17.10014,
    "2001": -8.00001,
    "2003": 3.3563,
    "2004": 7.7435,
    "2005": 6.64617,
    "2006": 3.84046,
    "2007": 7.32729,
    "2008": 0.39012,
    "2009": -12.3057,
    "2011": 10.2,
    "2012": -0.2,
    "2013": 6.6,
    "2014": 4.3,
    "2015": 4.7,
    "2016": -0.7,
    "2017": 7.6,
    "2018": 0.5,
    "2019": 7.16558041,
    "2020": -9.580773761,
    "2021": 16.968385150298
  }
}